dynbatcher/__init__.py
dynbatcher/data_processing.py
dynbatcher/utils.py
dynbatcher-1.1.0.dist-info/LICENSE
dynbatcher-1.1.0.dist-info/METADATA
dynbatcher-1.1.0.dist-info/WHEEL
dynbatcher-1.1.0.dist-info/top_level.txt
dynbatcher-1.1.0.dist-info/RECORD
