Metadata-Version: 2.1
Name: dynbatcher
Version: 1.1.0
Summary: A package for creation of dataloader with dynamic batch sizes in PyTorch
Home-page: https://github.com/robuno/dynbatcher
Author: Unat T.
License: MIT
Classifier: Programming Language :: Python :: 3
Classifier: License :: OSI Approved :: MIT License
Classifier: Operating System :: OS Independent
Requires-Python: >=3.6
License-File: LICENSE
Requires-Dist: torch
Requires-Dist: matplotlib
